setup.py
corenetwork/__init__.py
corenetwork/api_mixin.py
corenetwork/app.py
corenetwork/command_line_mixin.py
corenetwork/corosync_mixin.py
corenetwork/driver_interface.py
corenetwork/hook_interface.py
corenetwork/network_mixin.py
corenetwork/os_mixin.py
corenetwork/storage_mixin.py
corenetwork/webserver_mixin.py
corenetwork.egg-info/PKG-INFO
corenetwork.egg-info/SOURCES.txt
corenetwork.egg-info/dependency_links.txt
corenetwork.egg-info/requires.txt
corenetwork.egg-info/top_level.txt
corenetwork/drivers/__init__.py
corenetwork/drivers/bird.py
corenetwork/drivers/core_default.py
corenetwork/drivers/network_quagga.py
corenetwork/drivers/network_vxlan.py
corenetwork/drivers/node_default.py
corenetwork/drivers/node_ssh.py
corenetwork/drivers/vm_default.py
corenetwork/exceptions/__init__.py
corenetwork/exceptions/config.py
corenetwork/hooks/__init__.py
corenetwork/hooks/logs_dump.py
corenetwork/migrations/0001_initial.py
corenetwork/migrations/__init__.py
corenetwork/models/__init__.py
corenetwork/models/message.py
corenetwork/models/tag.py
corenetwork/utils/__init__.py
corenetwork/utils/config.py
corenetwork/utils/db_router.py
corenetwork/utils/logger.py
corenetwork/utils/renderer.py
corenetwork/utils/system.py