Metadata-Version: 1.1
Name: corenetwork
Version: 17.4.1
Summary: CoreCluster common networking package
Home-page: http://cloudover.org/corecluster/
Author: Marta Nabozny
Author-email: martastrzet@gmail.com
License: UNKNOWN
Download-URL: https://github.com/cloudOver/CoreCluster/archive/master.zip
Keywords: corecluster,corenetwork,cloudover,cloud
Platform: UNKNOWN
